gloo_internal/__init__.py
gloo_internal/api.py
gloo_internal/api_types.py
gloo_internal/common.py
gloo_internal/context_manager.py
gloo_internal/env.py
gloo_internal/llm_client.py
gloo_internal/llm_clients/__init__.py
gloo_internal/llm_clients/anthropic_client.py
gloo_internal/llm_clients/base_client.py
gloo_internal/llm_clients/factory.py
gloo_internal/llm_clients/openai_client.py
gloo_internal/logging.py
gloo_internal/py.typed
gloo_internal/test_context_manager.py
gloo_internal/tracer.py
gloo_py/__init__.py
gloo_py/py.typed
gloo_py/stringify/__init__.py
gloo_py/testing/__init__.py
gloo_stringify/__init__.py
gloo_stringify/errors.py
gloo_stringify/py.typed
gloo_stringify/stringify.py
gloo_stringify/stringify_class.py
gloo_stringify/stringify_enum.py
gloo_stringify/stringify_list.py
gloo_stringify/stringify_optional.py
gloo_stringify/stringify_primitive.py
gloo_stringify/stringify_union.py
gloo_stringify/tests/__init__.py
gloo_stringify/tests/test_stringify.py
gloo_testing/__init__.py
gloo_testing/py.typed
gloo_testing/pytest_gloo.py
gloo_lib-1.3.1.dist-info/METADATA
gloo_lib-1.3.1.dist-info/WHEEL
gloo_lib-1.3.1.dist-info/entry_points.txt
gloo_lib-1.3.1.dist-info/RECORD
