Metadata-Version: 2.1
Name: gloo-lib
Version: 1.3.1
Summary: 
Author: Gloo
Author-email: contact@trygloo.com
Requires-Python: >=3.8,<4.0
Classifier: Programming Language :: Python :: 3
Classifier: Programming Language :: Python :: 3.8
Classifier: Programming Language :: Python :: 3.9
Classifier: Programming Language :: Python :: 3.10
Classifier: Programming Language :: Python :: 3.11
Requires-Dist: aiohttp (>=3.8.5,<4.0.0)
Requires-Dist: anthropic (>=0.3.11,<0.4.0)
Requires-Dist: coloredlogs (>=15.0.1,<16.0.0)
Requires-Dist: openai (>=0.27.9)
Requires-Dist: pydantic (>=2.3.0,<3.0.0)
Requires-Dist: pytest (>=7.4.2,<8.0.0)
Requires-Dist: pytest-asyncio (>=0.21.1,<0.22.0)
Requires-Dist: python-dotenv (>=1.0.0,<2.0.0)
Requires-Dist: types-requests (>=2.31.0.2,<3.0.0.0)
